eje.py
eje-3.0.1.dist-info/LICENSE
eje-3.0.1.dist-info/METADATA
eje-3.0.1.dist-info/WHEEL
eje-3.0.1.dist-info/top_level.txt
eje-3.0.1.dist-info/RECORD
