Metadata-Version: 2.1
Name: eje
Version: 3.0.1
Summary: UNKNOWN
Home-page: https://github.com/cganterh/eje
Author: Cristóbal Ganter
Author-email: cganterh@gmail.com
License: UNKNOWN
Platform: UNKNOWN
Requires-Dist: setuptools (>=42.0)
Requires-Dist: tornado (~=6.0)
